impulsare_logger
